musicbox_mpd/__about__.py
musicbox_mpd/__init__.py
musicbox_mpd/__main__.py
musicbox_mpd/data.py
musicbox_mpd/main.py
musicbox_mpd/musicplayer.py
musicbox_mpd/playcounter.py
musicbox_mpd/startup.py
musicbox_mpd/ui/5by7.ttf
musicbox_mpd/ui/default.gif
musicbox_mpd/ui/favicon.ico
musicbox_mpd/ui/settings.html
musicbox_mpd/ui/ui.css
musicbox_mpd/ui/ui.html
musicbox_mpd/ui/ui.js
musicbox_mpd/ui/img/compact-disc-solid.svg
musicbox_mpd/ui/img/floppy-disk-solid.svg
musicbox_mpd/ui/img/forward-solid.svg
musicbox_mpd/ui/img/forward-step-solid.svg
musicbox_mpd/ui/img/guitar-solid.svg
musicbox_mpd/ui/img/house-solid.svg
musicbox_mpd/ui/img/list-ul-solid.svg
musicbox_mpd/ui/img/magnifying-glass-solid.svg
musicbox_mpd/ui/img/minus-solid.svg
musicbox_mpd/ui/img/music-solid.svg
musicbox_mpd/ui/img/pause-solid.svg
musicbox_mpd/ui/img/play-solid.svg
musicbox_mpd/ui/img/plus-solid.svg
musicbox_mpd/ui/img/stop-solid.svg
musicbox_mpd/ui/img/trash-solid.svg
musicbox_mpd-0.3.1.dist-info/METADATA
musicbox_mpd-0.3.1.dist-info/WHEEL
musicbox_mpd-0.3.1.dist-info/entry_points.txt
musicbox_mpd-0.3.1.dist-info/licenses/LICENSE.txt
musicbox_mpd-0.3.1.dist-info/RECORD
