Metadata-Version: 2.4
Name: musicbox-mpd
Version: 0.3.1
Project-URL: Documentation, https://github.com/malworthy/musicbox-mpd#readme
Project-URL: Issues, https://github.com/malworthy/musicbox-mpd/issues
Project-URL: Source, https://github.com/malworthy/musicbox-mpd
Author: Malcolm Worthy
License-Expression: MIT
License-File: LICENSE.txt
Keywords: mpd,mpd client,musicbox,musicbox-mpd
Classifier: Development Status :: 3 - Alpha
Classifier: Programming Language :: Python
Classifier: Programming Language :: Python :: 3.8
Classifier: Programming Language :: Python :: 3.9
Classifier: Programming Language :: Python :: 3.10
Classifier: Programming Language :: Python :: 3.11
Classifier: Programming Language :: Python :: 3.12
Classifier: Programming Language :: Python :: Implementation :: CPython
Classifier: Programming Language :: Python :: Implementation :: PyPy
Requires-Python: >=3.8
Requires-Dist: python-mpd2
Requires-Dist: starlette
Requires-Dist: uvicorn[standard]
